{
  "id": 113245,
  "title": "Save search result as a new view in mywork",
  "slug": "save-search-result-as-a-new-view-in-mywork",
  "categoryId": 7,
  "tagIds": [
    97,
    196
  ],
  "createdAt": "2025-04-16T05:59:15.248Z",
  "lastPostedAt": "2025-04-16T05:59:15.311Z",
  "postsCount": 1,
  "excerpt": "I just started exploring the myWork. I thought it could be very useful to enable a custom view based on the search result (or filter result) similar to what the standard board does. That way, there will be always a dedic&hellip;",
  "solvedPostId": null,
  "likeCount": 0,
  "views": 7,
  "posts": [
    {
      "id": 227104,
      "postNumber": 1,
      "createdAt": "2025-04-16T05:59:15.311Z",
      "author": "Ben_psi (Ben Liu)",
      "cookedHtml": "<p>I just started exploring the myWork. I thought it could be very useful to enable a custom view based on the search result (or filter result) similar to what the standard board does. That way, there will be always a dedicated view for certain tasks. thoughts?</p>"
    }
  ]
}