{
  "id": 120126,
  "title": "Making Connected Board Column available to non logged in users of forms",
  "slug": "making-connected-board-column-available-to-non-logged-in-users-of-forms",
  "categoryId": 7,
  "tagIds": [
    462
  ],
  "createdAt": "2025-09-19T10:07:04.913Z",
  "lastPostedAt": "2025-09-19T10:07:04.986Z",
  "postsCount": 1,
  "excerpt": "Description\nMake Workforms use similar functionality to Easyforms. \nWhat are you trying to achieve\nWe have external clients who send us job requests. There is a lot of information that our team needs in order to complete&hellip;",
  "solvedPostId": null,
  "likeCount": 0,
  "views": 16,
  "posts": [
    {
      "id": 238877,
      "postNumber": 1,
      "createdAt": "2025-09-19T10:07:04.986Z",
      "author": "AmyQ (Amy Quayle)",
      "cookedHtml": "<h3><a name=\"p-238877-description-1\" class=\"anchor\" href=\"#p-238877-description-1\"></a>Description</h3>\n<p>Make Workforms use similar functionality to Easyforms.</p>\n<h3><a name=\"p-238877-what-are-you-trying-to-achieve-2\" class=\"anchor\" href=\"#p-238877-what-are-you-trying-to-achieve-2\"></a>What are you trying to achieve</h3>\n<p>We have external clients who send us job requests. There is a lot of information that our team needs in order to complete jobs that we do not wish to ask our clients each time on a form. Now, Easyforms does do this, however, it has other limitations which means it doesn’t work as well as Workforms. Surely if Easyforms can do it Workforms can? We would really like not to have to give guest access to <a href=\"http://Monday.com\" rel=\"noopener nofollow ugc\">Monday.com</a> to clients if we can avoid it.</p>"
    }
  ]
}