{
  "id": 30759,
  "title": "Kann man eine Zeitleiste auch mit Stunden angeben?",
  "slug": "kann-man-eine-zeitleiste-auch-mit-stunden-angeben",
  "categoryId": 7,
  "tagIds": [
    13
  ],
  "createdAt": "2022-01-31T11:07:56.865Z",
  "lastPostedAt": "2024-09-13T13:52:44.277Z",
  "postsCount": 2,
  "excerpt": "Kann man eine Zeitleiste auch mit Stunden angeben, wenn eine Aufgabe z.B. 2.5 Tage geht. \nDann sollte ersichtlich sein, dass die Maschine noch nicht den ganzen Tag verplant ist.",
  "solvedPostId": null,
  "likeCount": 0,
  "views": 1383,
  "posts": [
    {
      "id": 75530,
      "postNumber": 1,
      "createdAt": "2022-01-31T11:07:56.959Z",
      "author": "MiGla (Michael Glaus)",
      "cookedHtml": "<p>Kann man eine Zeitleiste auch mit Stunden angeben, wenn eine Aufgabe z.B. 2.5 Tage geht.<br />\nDann sollte ersichtlich sein, dass die Maschine noch nicht den ganzen Tag verplant ist.</p>"
    },
    {
      "id": 201121,
      "postNumber": 2,
      "createdAt": "2024-09-13T13:52:44.277Z",
      "author": "vonkreutzbruck (Benjamin Kreutzbruck)",
      "cookedHtml": "<p>Ich suche die gleiche Funktion . September 2024…</p>"
    }
  ]
}