{
  "id": 83939,
  "title": "What internal messaging tool do you use?",
  "slug": "what-internal-messaging-tool-do-you-use",
  "categoryId": 6,
  "tagIds": [
    5
  ],
  "createdAt": "2024-04-15T09:53:29.276Z",
  "lastPostedAt": "2024-04-24T10:43:29.339Z",
  "postsCount": 3,
  "excerpt": "Hi! I’m Ben from the monday.com product team! I’m working with our integration partners and would love to hear from you about how you communicate with your co-workers. \nPlease feel free to comment below, we’d love to hea&hellip;",
  "solvedPostId": null,
  "likeCount": 0,
  "views": 286,
  "posts": [
    {
      "id": 178648,
      "postNumber": 1,
      "createdAt": "2024-04-15T09:53:29.353Z",
      "author": "Benjo (Ben Johnston)",
      "cookedHtml": "<p>Hi! I’m Ben from the <a href=\"http://monday.com\">monday.com</a> product team! I’m working with our integration partners and would love to hear from you about how you communicate with your co-workers.</p>\n<p>Please feel free to comment below, we’d love to hear your thoughts!</p>\n<div class=\"poll\">\n<div class=\"poll-container\"><ul>\n<li>Slack</li>\n<li>Microsoft Teams</li>\n<li>Google Chat</li>\n<li>WhatsApp</li>\n<li>Zoom Chat</li>\n<li>Other</li>\n</ul>\n</div>\n<div class=\"poll-info\">\n<div class=\"poll-info_counts\">\n<div class=\"poll-info_counts-count\">\n<span class=\"info-number\">0</span>\n<span class=\"info-label\">voters</span>\n</div>\n</div>\n</div>\n</div>"
    },
    {
      "id": 178649,
      "postNumber": 2,
      "createdAt": "2024-04-15T09:54:03.580Z",
      "author": "Julietteb (Juliette )",
      "cookedHtml": ""
    },
    {
      "id": 180665,
      "postNumber": 3,
      "createdAt": "2024-04-24T10:43:29.339Z",
      "author": "Julietteb (Juliette )",
      "cookedHtml": "<p>Great question!</p>"
    }
  ]
}