{
  "items": [
    {
      "id": 13504,
      "title": "Policy on apps manipulating monday.com's using a browser extension",
      "slug": "policy-on-apps-manipulating-monday-coms-using-a-browser-extension",
      "excerpt": "Does monday.com have a policy towards an app that depends on a browser extension which manipulates the monday.com user interface? A quick review of some other app marketplaces forbids this. For example, the Google Worksp&hellip;",
      "postsCount": 4,
      "lastPostedAt": "2021-03-12T14:22:40.545Z",
      "createdAt": "2020-11-21T18:41:48.112Z",
      "bumpedAt": "2021-03-12T14:22:26.413Z",
      "solvedPostId": null,
      "likeCount": 1,
      "views": 1508
    },
    {
      "id": 17482,
      "title": "File upload SDK",
      "slug": "file-upload-sdk",
      "excerpt": "Hey Everyone! \nI’m sorry for making a duplicate of my old post, but this one is a bit different. ​ \nI found out that there’s now a SDK way of file upload rather than having an authentication flow which is what I have now&hellip;",
      "postsCount": 5,
      "lastPostedAt": "2021-03-19T12:55:26.492Z",
      "createdAt": "2021-03-11T00:36:31.980Z",
      "bumpedAt": "2021-03-12T12:55:13.358Z",
      "solvedPostId": null,
      "likeCount": 3,
      "views": 2358
    },
    {
      "id": 12293,
      "title": "API - Delete Groups Mutation issue",
      "slug": "api-delete-groups-mutation-issue",
      "excerpt": "Hi there, \nJust a ticket to mention Delete Group method in the V2 Mutation API is not working whil I get a deleted “tru” result. Awkward! \nExample, \nPayload sent: \n{&quot;query&quot;:&quot;mutation {\\ndelete_group (board_id:804412871, &hellip;",
      "postsCount": 6,
      "lastPostedAt": "2021-03-12T12:37:13.444Z",
      "createdAt": "2020-10-19T11:19:48.260Z",
      "bumpedAt": "2021-03-12T12:37:13.444Z",
      "solvedPostId": null,
      "likeCount": 0,
      "views": 1117
    },
    {
      "id": 17532,
      "title": "Power BI connector",
      "slug": "power-bi-connector",
      "excerpt": "Does anyone know of a sure way to get data into Power BI? \nI’ve tried this Loading GraphQL data (monday.com API v2) into PowerBI · GitHub \nHowever it’s not working returning an error  “We found extra characters at the en&hellip;",
      "postsCount": 5,
      "lastPostedAt": "2021-03-12T12:33:02.391Z",
      "createdAt": "2021-03-11T17:55:34.537Z",
      "bumpedAt": "2021-03-12T12:33:02.391Z",
      "solvedPostId": null,
      "likeCount": 0,
      "views": 2522
    },
    {
      "id": 17497,
      "title": "Get SubItem values through API",
      "slug": "get-subitem-values-through-api",
      "excerpt": "Hi. \nI need to gel all subitem values for the specific board. \nMy steps: \n\nGetting board (id 1087268631) items and looking for sub-items.\n\n  \nSo, ids for sub items are [1087268826, 1087268835, 1087300566, 1087301038] \n\nG&hellip;",
      "postsCount": 6,
      "lastPostedAt": "2021-03-19T12:53:24.416Z",
      "createdAt": "2021-03-11T06:56:21.203Z",
      "bumpedAt": "2021-03-12T10:38:41.354Z",
      "solvedPostId": null,
      "likeCount": 2,
      "views": 2277
    },
    {
      "id": 17463,
      "title": "Why is there a limit of subtasks you can create in a board?",
      "slug": "why-is-there-a-limit-of-subtasks-you-can-create-in-a-board",
      "excerpt": "Our board is maxed out for 10,000 subtasks. Why is there a limit&gt;? \nAlso, we archived some of them but then we have no way to see how many seats are being freed so far. Is there anyway to see how much we freed for the en&hellip;",
      "postsCount": 10,
      "lastPostedAt": "2021-03-11T19:39:51.740Z",
      "createdAt": "2021-03-10T17:00:06.704Z",
      "bumpedAt": "2021-03-11T19:39:51.740Z",
      "solvedPostId": null,
      "likeCount": 0,
      "views": 2554
    },
    {
      "id": 17402,
      "title": "Accessing the storage via PHP",
      "slug": "accessing-the-storage-via-php",
      "excerpt": "Hey, \nI was assigned the task to build an integration using PHP. I cannot use NodeJS for my task so I was wandering how can I use the Storage API outside the SDK implementations? \nIt seems like you API docs and PHP quick&hellip;",
      "postsCount": 9,
      "lastPostedAt": "2021-03-11T14:17:52.042Z",
      "createdAt": "2021-03-09T16:16:53.853Z",
      "bumpedAt": "2021-03-11T14:17:52.042Z",
      "solvedPostId": null,
      "likeCount": 3,
      "views": 1404
    },
    {
      "id": 13748,
      "title": "\"This page is restricted Error\" in Monday App",
      "slug": "this-page-is-restricted-error-in-monday-app",
      "excerpt": "Hi All, \nI have developed Monday App with Monday SDK, It is working very well for our company domain “symbo-team.monday.com”.But when I install it on another company domain like “sky-team.monday.com” then I get the error&hellip;",
      "postsCount": 9,
      "lastPostedAt": "2021-03-11T09:39:33.852Z",
      "createdAt": "2020-11-29T07:23:00.228Z",
      "bumpedAt": "2021-03-11T09:39:33.852Z",
      "solvedPostId": null,
      "likeCount": 3,
      "views": 2101
    },
    {
      "id": 12230,
      "title": "Add item trigger not triggered when duplicating a group",
      "slug": "add-item-trigger-not-triggered-when-duplicating-a-group",
      "excerpt": "Hi team, \nWhen duplicating a (set of) items, the “add item” webhook is triggered as expected. However when duplicating a group with existing items in it the “add item” is not triggered. This is a serious problem for one &hellip;",
      "postsCount": 8,
      "lastPostedAt": "2021-03-10T17:36:40.043Z",
      "createdAt": "2020-10-16T11:15:35.684Z",
      "bumpedAt": "2021-03-10T17:36:29.718Z",
      "solvedPostId": null,
      "likeCount": 4,
      "views": 3035
    },
    {
      "id": 12932,
      "title": "API performance of heavily used board degrading over time?",
      "slug": "api-performance-of-heavily-used-board-degrading-over-time",
      "excerpt": "Hi, \nOn my Monday account we have a Monday board which is used to store programatically calculated values. It basically contains for each month the billability percentage of each team in our company. This percentage is r&hellip;",
      "postsCount": 8,
      "lastPostedAt": "2021-03-10T17:33:06.028Z",
      "createdAt": "2020-11-06T13:39:16.748Z",
      "bumpedAt": "2021-03-10T17:32:57.778Z",
      "solvedPostId": null,
      "likeCount": 0,
      "views": 1702
    },
    {
      "id": 12082,
      "title": "Aggregate data through the V2 API",
      "slug": "aggregate-data-through-the-v2-api",
      "excerpt": "Hi, \nDoes anyone know if aggregate data can be queried through the API?",
      "postsCount": 5,
      "lastPostedAt": "2021-03-10T14:47:50.516Z",
      "createdAt": "2020-10-12T10:51:43.673Z",
      "bumpedAt": "2021-03-10T14:47:42.139Z",
      "solvedPostId": null,
      "likeCount": 0,
      "views": 1434
    },
    {
      "id": 13862,
      "title": "Dashboard in Workspace Template App not working",
      "slug": "dashboard-in-workspace-template-app-not-working",
      "excerpt": "My app is a workspace template with the main view as a dasboard written as a custom app. The dashboard works in the original workspace, but when I try to install the template into another account it’s broken. I don’t thi&hellip;",
      "postsCount": 6,
      "lastPostedAt": "2021-03-17T16:09:50.763Z",
      "createdAt": "2020-12-02T15:54:48.876Z",
      "bumpedAt": "2021-03-10T13:35:42.068Z",
      "solvedPostId": null,
      "likeCount": 0,
      "views": 1362
    },
    {
      "id": 12835,
      "title": "User Unauthorized to perform action - 403",
      "slug": "user-unauthorized-to-perform-action-403",
      "excerpt": "Hello, \nI am trying to perform the following action and getting an error or status code 403 “user unauthorized to perform action”. \nAction: \nmutation { \n                create_item (board_id: 344121329, group_id: new_gro&hellip;",
      "postsCount": 11,
      "lastPostedAt": "2021-03-15T13:53:47.709Z",
      "createdAt": "2020-11-03T22:43:23.176Z",
      "bumpedAt": "2021-03-10T13:27:34.255Z",
      "solvedPostId": null,
      "likeCount": 1,
      "views": 5366
    },
    {
      "id": 17389,
      "title": "Show notification message/popup on board",
      "slug": "show-notification-message-popup-on-board",
      "excerpt": "Hi, \nI have developed a custom integration which custom action(node js). We have a requirement to show a notification message real time to user on board. \nI tried using create_notification api, but its showing message in&hellip;",
      "postsCount": 8,
      "lastPostedAt": "2021-03-10T11:44:32.102Z",
      "createdAt": "2021-03-09T14:15:59.640Z",
      "bumpedAt": "2021-03-10T11:44:32.102Z",
      "solvedPostId": null,
      "likeCount": 0,
      "views": 2639
    },
    {
      "id": 17231,
      "title": "Sdk openItemCard does not detect changes in item name",
      "slug": "sdk-openitemcard-does-not-detect-changes-in-item-name",
      "excerpt": "Hey guys, \nI read some problems were fixed on the monday.execute(‘openItemCard’) command, but I am still getting some (loading sdk from cdn). \nBoth update and column kinds allow us to edit the item name. \nHowever it does&hellip;",
      "postsCount": 7,
      "lastPostedAt": "2021-03-16T19:16:40.700Z",
      "createdAt": "2021-03-06T10:18:36.466Z",
      "bumpedAt": "2021-03-09T19:16:31.977Z",
      "solvedPostId": null,
      "likeCount": 1,
      "views": 1132
    },
    {
      "id": 17274,
      "title": "Getting 'Message' Field Type Property Values",
      "slug": "getting-message-field-type-property-values",
      "excerpt": "I’m building a new Integration App that has a Recipe that notifies a user in another platform whenever an Item’s Status changes. Similar to the Slack integration recipe, I would like to allow the user to input a custom m&hellip;",
      "postsCount": 6,
      "lastPostedAt": "2021-03-12T14:29:02.457Z",
      "createdAt": "2021-03-08T03:08:46.480Z",
      "bumpedAt": "2021-03-08T05:39:06.485Z",
      "solvedPostId": null,
      "likeCount": 2,
      "views": 1467
    },
    {
      "id": 17263,
      "title": "Authentication using webhook to my backend",
      "slug": "authentication-using-webhook-to-my-backend",
      "excerpt": "Hello!  im building my first monday app and im having some issues.  my app has a board view and an integration with a webhook to my backend.  im registering to events on the board such as column changes, and im manually &hellip;",
      "postsCount": 6,
      "lastPostedAt": "2021-03-12T14:27:49.574Z",
      "createdAt": "2021-03-07T17:51:11.730Z",
      "bumpedAt": "2021-03-07T21:54:23.944Z",
      "solvedPostId": null,
      "likeCount": 1,
      "views": 1808
    },
    {
      "id": 16854,
      "title": "Activity Logs and updates",
      "slug": "activity-logs-and-updates",
      "excerpt": "Hi guys, \nIs it possible to get updates through activity logs? Currently I am syncing board item data using from/to through Activity Logs. Something like: \n“query”: &quot;{ boards (ids: xxxxxxxxxx){ activity_logs(from: &quot;2021-&hellip;",
      "postsCount": 8,
      "lastPostedAt": "2021-03-14T16:50:36.438Z",
      "createdAt": "2021-02-26T06:24:01.970Z",
      "bumpedAt": "2021-03-07T16:49:52.888Z",
      "solvedPostId": null,
      "likeCount": 3,
      "views": 2069
    },
    {
      "id": 13492,
      "title": "Defect - workspace templates with dashboards broken",
      "slug": "defect-workspace-templates-with-dashboards-broken",
      "excerpt": "Hello! \nI have mentioned this personally to @Ben, @VladMonday, and @dipro \nPutting this here so I can follow the development. This defect is causing a lot of disappointment and curious if this is on your radar. workspace&hellip;",
      "postsCount": 6,
      "lastPostedAt": "2021-03-15T14:05:26.273Z",
      "createdAt": "2020-11-21T08:19:10.936Z",
      "bumpedAt": "2021-03-05T18:42:33.423Z",
      "solvedPostId": null,
      "likeCount": 0,
      "views": 1379
    },
    {
      "id": 13015,
      "title": "React Version Support",
      "slug": "react-version-support",
      "excerpt": "The Quickstart guide uses React 16.13.0. Is it necessary to use this version of React to create an app? Since the app is rendered in an iframe and your are interacted with Monday through the API would it be possible to u&hellip;",
      "postsCount": 3,
      "lastPostedAt": "2021-03-12T14:28:38.087Z",
      "createdAt": "2020-11-10T00:45:45.506Z",
      "bumpedAt": "2021-03-05T18:20:44.779Z",
      "solvedPostId": null,
      "likeCount": 0,
      "views": 1955
    },
    {
      "id": 13333,
      "title": "How to create an integration column?",
      "slug": "how-to-create-an-integration-column",
      "excerpt": "I am trying integrate our app with Monday.com by using custom trigger and CREATE AN ITEM WITH MAPPING. Can I know how will I be able to create an integration column along with this flow of creating an item? \nAlso, will I&hellip;",
      "postsCount": 6,
      "lastPostedAt": "2021-03-12T14:29:14.504Z",
      "createdAt": "2020-11-17T09:35:35.360Z",
      "bumpedAt": "2021-03-05T18:14:37.317Z",
      "solvedPostId": null,
      "likeCount": 0,
      "views": 3576
    },
    {
      "id": 17115,
      "title": "Custom Integration",
      "slug": "custom-integration",
      "excerpt": "Hello, \nI would like to have some custom integration that allows matrics/value from other platform to my Monday boards. \nFor example I Monday board that have 5 domains site that I want to keep track for its expired date. &hellip;",
      "postsCount": 3,
      "lastPostedAt": "2021-03-04T13:49:10.749Z",
      "createdAt": "2021-03-04T06:36:58.231Z",
      "bumpedAt": "2021-03-04T13:49:10.749Z",
      "solvedPostId": null,
      "likeCount": 1,
      "views": 1415
    },
    {
      "id": 16948,
      "title": "Create a PHP API",
      "slug": "create-a-php-api",
      "excerpt": "Hello, \nI’m new with Monday API. I created an API with quickstart-react. My team is not familiar with React and we’d like to create an API with PHP instead. We’ve tried following the steps in https://support.monday.com/h&hellip;",
      "postsCount": 7,
      "lastPostedAt": "2021-03-10T20:24:45.369Z",
      "createdAt": "2021-03-01T08:15:07.270Z",
      "bumpedAt": "2021-03-03T20:24:38.535Z",
      "solvedPostId": null,
      "likeCount": 5,
      "views": 1595
    },
    {
      "id": 12497,
      "title": "Notification payload",
      "slug": "notification-payload",
      "excerpt": "Hi Monday Team, \nIn your API documentation, for creating notifications, it says we can add JSON payload, but I am getting 500s constantly when I try to add it (without that argument it works well): \n    monday.api(`\n    &hellip;",
      "postsCount": 7,
      "lastPostedAt": "2021-03-03T15:29:35.978Z",
      "createdAt": "2020-10-25T08:40:50.723Z",
      "bumpedAt": "2021-03-03T15:29:35.978Z",
      "solvedPostId": null,
      "likeCount": 0,
      "views": 2855
    },
    {
      "id": 13730,
      "title": "Notification Handling via Graphql",
      "slug": "notification-handling-via-graphql",
      "excerpt": "Hello everybody, \nI am trying to use the Notification System for an Application. I am using the api method as described in https://monday.com/developers/apps/sdk. When sending a mutation api call as described here https:&hellip;",
      "postsCount": 6,
      "lastPostedAt": "2021-03-10T15:29:42.348Z",
      "createdAt": "2020-11-27T19:24:47.324Z",
      "bumpedAt": "2021-03-03T15:27:43.682Z",
      "solvedPostId": null,
      "likeCount": 1,
      "views": 2238
    },
    {
      "id": 14544,
      "title": "Fetching items by column value and group id",
      "slug": "fetching-items-by-column-value-and-group-id",
      "excerpt": "Hi, \nI have a board with two groups, and i want to be able to fetch an item by a specific column id, but it exists on both groups. \nIs it possible to fetch items by column value and group id at the same time?",
      "postsCount": 6,
      "lastPostedAt": "2021-03-03T14:54:55.456Z",
      "createdAt": "2021-01-03T12:52:25.530Z",
      "bumpedAt": "2021-03-03T14:54:55.456Z",
      "solvedPostId": null,
      "likeCount": 0,
      "views": 3863
    },
    {
      "id": 16127,
      "title": "Mutation giving error",
      "slug": "mutation-giving-error",
      "excerpt": "I am trying to build a Power BI Report that can modify information on Monday.com. \nThe below query works to get information from a board: \n“{”“query”“: ““query { boards(ids: ####)  {activity_logs(limit: 1000) {event, ent&hellip;",
      "postsCount": 14,
      "lastPostedAt": "2021-03-03T14:16:15.499Z",
      "createdAt": "2021-02-10T15:00:36.375Z",
      "bumpedAt": "2021-03-03T14:16:15.499Z",
      "solvedPostId": null,
      "likeCount": 1,
      "views": 2297
    },
    {
      "id": 16658,
      "title": "Fetching columns title and id",
      "slug": "fetching-columns-title-and-id",
      "excerpt": "Hi, \nI am trying to fetch the column title and their id’s of a particular board by passing its id(boardId) but I am getting the result of all the boards that are there in my workspace. \nCan anybody help me out if i want &hellip;",
      "postsCount": 10,
      "lastPostedAt": "2021-03-02T08:38:14.892Z",
      "createdAt": "2021-02-23T08:37:45.015Z",
      "bumpedAt": "2021-03-02T08:38:14.892Z",
      "solvedPostId": null,
      "likeCount": 0,
      "views": 1939
    },
    {
      "id": 16681,
      "title": "File upload extension issue",
      "slug": "file-upload-extension-issue",
      "excerpt": "Hi all, \nI’m developing an application for the marketplace and facing an issue with the files API. \nExcept for .png files, all the files I’m trying to upload, contain a ‘null’ extension and as a result, the file cannot b&hellip;",
      "postsCount": 9,
      "lastPostedAt": "2021-03-01T22:39:21.325Z",
      "createdAt": "2021-02-23T14:56:00.066Z",
      "bumpedAt": "2021-03-01T22:39:21.325Z",
      "solvedPostId": null,
      "likeCount": 3,
      "views": 3532
    },
    {
      "id": 16895,
      "title": "Failed mutation",
      "slug": "failed-mutation",
      "excerpt": "Hey everyone, \nWhen we try to mutate the values of one item , the result is an error!. Funny enough we made similar mutation before an after, and those were a success \nThe mutation we use is: \nmutation { \nchange_column_v&hellip;",
      "postsCount": 4,
      "lastPostedAt": "2021-03-01T14:41:44.713Z",
      "createdAt": "2021-02-26T21:46:33.822Z",
      "bumpedAt": "2021-03-01T14:41:44.713Z",
      "solvedPostId": null,
      "likeCount": 1,
      "views": 1378
    },
    {
      "id": 16714,
      "title": "I am trying to have a custom field",
      "slug": "i-am-trying-to-have-a-custom-field",
      "excerpt": "I am trying to have a custom field and the situation is like when I opt for dynamic mapping and mention the dependency to be the boardId, I easily get the boardId but when i choose it to be the list and mention the depen&hellip;",
      "postsCount": 9,
      "lastPostedAt": "2021-02-26T14:39:14.437Z",
      "createdAt": "2021-02-24T06:44:53.351Z",
      "bumpedAt": "2021-02-26T14:39:14.437Z",
      "solvedPostId": null,
      "likeCount": 0,
      "views": 1958
    },
    {
      "id": 6659,
      "title": "$39/Month to be a developer for apps?",
      "slug": "39-month-to-be-a-developer-for-apps",
      "excerpt": "I created a Monday app. Now that my trial is over, I’m being asked to pay $39/month to continue using Monday. Is there such a thing as a developer/test Monday account? \nThe Apple Developer Program, for example, cost only&hellip;",
      "postsCount": 11,
      "lastPostedAt": "2021-02-25T14:23:19.419Z",
      "createdAt": "2020-04-23T22:30:40.595Z",
      "bumpedAt": "2021-02-25T14:23:02.215Z",
      "solvedPostId": null,
      "likeCount": 1,
      "views": 2603
    },
    {
      "id": 15168,
      "title": "Change_multiple_column_values doesn't work as expected",
      "slug": "change-multiple-column-values-doesnt-work-as-expected",
      "excerpt": "Hi, \nI’m trying to use change_multiple_column_values using Javascript: \nlet query5 =\n&#39;mutation ($boardId: Int!, $columnVals: JSON!, $itemId: Int!) { change_multiple_column_values (board_id: $boardId, item_id: $itemId, co&hellip;",
      "postsCount": 6,
      "lastPostedAt": "2021-03-04T12:05:13.757Z",
      "createdAt": "2021-01-19T14:38:42.281Z",
      "bumpedAt": "2021-02-25T12:04:54.191Z",
      "solvedPostId": null,
      "likeCount": 1,
      "views": 2651
    },
    {
      "id": 16787,
      "title": "Bug in API (complexity object)",
      "slug": "bug-in-api-complexity-object",
      "excerpt": "Removing complexity  object from query fixes my problem. \nPreviously this worked, but now no.",
      "postsCount": 3,
      "lastPostedAt": "2021-02-25T11:55:16.625Z",
      "createdAt": "2021-02-25T07:16:33.886Z",
      "bumpedAt": "2021-02-25T11:55:16.625Z",
      "solvedPostId": null,
      "likeCount": 1,
      "views": 1015
    },
    {
      "id": 7403,
      "title": "Create item with custom status and other columns values",
      "slug": "create-item-with-custom-status-and-other-columns-values",
      "excerpt": "Hi there, \nI’m trying to create task and define status of the task, but it is not easy to understand how to properly do this. \nMy query: \nmutation {create_item (board_id: 377902169, group_id: &quot;new_group18793&quot;, item_name:&hellip;",
      "postsCount": 7,
      "lastPostedAt": "2021-02-24T22:42:43.262Z",
      "createdAt": "2020-05-21T06:08:52.177Z",
      "bumpedAt": "2021-02-24T22:42:36.235Z",
      "solvedPostId": null,
      "likeCount": 2,
      "views": 6403
    },
    {
      "id": 16752,
      "title": "The abysmal nature of monday.com API",
      "slug": "the-abysmal-nature-of-monday-com-api",
      "excerpt": "Monday.com is a wonderful platform and it has the potential to grow even more but the current state of it’s API can have very serious negative consequences on it’s adoption by developers. The developers at Monday.com can&hellip;",
      "postsCount": 6,
      "lastPostedAt": "2021-02-24T19:18:00.464Z",
      "createdAt": "2021-02-24T15:42:18.133Z",
      "bumpedAt": "2021-02-24T19:18:00.464Z",
      "solvedPostId": null,
      "likeCount": 25,
      "views": 7347
    },
    {
      "id": 16460,
      "title": "Creating a new item with color columns updated",
      "slug": "creating-a-new-item-with-color-columns-updated",
      "excerpt": "I have a dashboard in which I am creating new items with a Python script. \nThe group I am creating items in has columns I would like to be populated with data as soon as an item is created. \nThis is an example of how i’d&hellip;",
      "postsCount": 8,
      "lastPostedAt": "2021-02-22T18:01:45.483Z",
      "createdAt": "2021-02-18T11:18:11.496Z",
      "bumpedAt": "2021-02-22T18:01:45.483Z",
      "solvedPostId": null,
      "likeCount": 2,
      "views": 2938
    },
    {
      "id": 16612,
      "title": "Choosing the right service",
      "slug": "choosing-the-right-service",
      "excerpt": "We would like to listen to events in our app and send data to our \nbackend wich in response will update the board data through monday api \nSo i saw the integrations feature, but i want a simple - when item created send r&hellip;",
      "postsCount": 5,
      "lastPostedAt": "2021-02-22T15:51:58.759Z",
      "createdAt": "2021-02-22T10:50:24.440Z",
      "bumpedAt": "2021-02-22T15:51:58.759Z",
      "solvedPostId": null,
      "likeCount": 1,
      "views": 1104
    },
    {
      "id": 16480,
      "title": "Connecting monday.com to PowerApps",
      "slug": "connecting-monday-com-to-powerapps",
      "excerpt": "Hi I am having trouble completing the setup of a Custom Connector from Microsoft PowerApps to monday.com.  My problem is that I get a Response of (200) &quot;“message”: “No query string was present”. \nI have tested that I can&hellip;",
      "postsCount": 6,
      "lastPostedAt": "2021-02-22T15:26:11.566Z",
      "createdAt": "2021-02-18T15:10:58.348Z",
      "bumpedAt": "2021-02-22T15:26:11.566Z",
      "solvedPostId": null,
      "likeCount": 0,
      "views": 7268
    },
    {
      "id": 16217,
      "title": "Calling WebService from Custom Action Run URL",
      "slug": "calling-webservice-from-custom-action-run-url",
      "excerpt": "Hi, \nI have a requirement to call a third party web service (SOAP) as part of the custom action. I can see that URL can be given “Run URL” for Custom Action. Can i call web service using this “Run URL”? \nRegards, \nRanjit&hellip;",
      "postsCount": 4,
      "lastPostedAt": "2021-02-19T03:43:25.847Z",
      "createdAt": "2021-02-12T12:52:21.989Z",
      "bumpedAt": "2021-02-19T03:43:25.847Z",
      "solvedPostId": null,
      "likeCount": 3,
      "views": 1341
    },
    {
      "id": 16101,
      "title": "[RELEASED] List Field Type based on boardId",
      "slug": "released-list-field-type-based-on-boardid",
      "excerpt": "Hi, \nI am trying to build a List Field Type based in Custom Blocks. I have a requirement to prepare \nthe list based on the boardId to which the recipe is being added. I found that only below parameters are passed to the &hellip;",
      "postsCount": 7,
      "lastPostedAt": "2021-02-24T22:50:56.640Z",
      "createdAt": "2021-02-10T02:54:48.683Z",
      "bumpedAt": "2021-02-19T03:41:41.522Z",
      "solvedPostId": null,
      "likeCount": 6,
      "views": 2086
    },
    {
      "id": 16459,
      "title": "File Column - Clear All 500 error",
      "slug": "file-column-clear-all-500-error",
      "excerpt": "Anyone else having any issues clearing a file column? \nI’m using the correct syntax but keep getting a 500 error, bot via my app and the monday playground. If I use an incorrect item_id or board_id I correctly get a 404.&hellip;",
      "postsCount": 10,
      "lastPostedAt": "2021-02-18T14:20:31.661Z",
      "createdAt": "2021-02-18T11:16:47.469Z",
      "bumpedAt": "2021-02-18T14:20:31.661Z",
      "solvedPostId": null,
      "likeCount": 0,
      "views": 1261
    },
    {
      "id": 16427,
      "title": "Monday.listen running more times than it should",
      "slug": "monday-listen-running-more-times-than-it-should",
      "excerpt": "Hello everyone! \nthis is my first topic here, so i hope that i’m doing it in the right section \nso, i1m having a strange problem, that i can’t seem to find the cause \ni made a simples app view in react, where i did a con&hellip;",
      "postsCount": 3,
      "lastPostedAt": "2021-03-08T12:44:10.921Z",
      "createdAt": "2021-02-17T19:01:56.266Z",
      "bumpedAt": "2021-02-18T12:50:34.772Z",
      "solvedPostId": null,
      "likeCount": 2,
      "views": 1076
    },
    {
      "id": 16443,
      "title": "API Location Update added, BUT still can't retrieve location data?",
      "slug": "api-location-update-added-but-still-cant-retrieve-location-data",
      "excerpt": "@Helen  - As of today, the Location column was updated in the API - THANKS FOR THAT… \nBut for some reason when I retrieve an item, the location data is blank. \nI’ve seen some items work … and location is there… but i jus&hellip;",
      "postsCount": 3,
      "lastPostedAt": "2021-02-18T12:24:45.945Z",
      "createdAt": "2021-02-18T04:10:17.661Z",
      "bumpedAt": "2021-02-18T12:24:45.945Z",
      "solvedPostId": null,
      "likeCount": 0,
      "views": 1056
    },
    {
      "id": 16343,
      "title": "Google Sheets API - Not creating column content",
      "slug": "google-sheets-api-not-creating-column-content",
      "excerpt": "Hi, \nI’ve used some of the examples on here to develop an API load for data to a new board (the final location will change) and I’ve got the script creating the new item but it won’t load the content we want for the colu&hellip;",
      "postsCount": 9,
      "lastPostedAt": "2021-03-04T01:22:13.063Z",
      "createdAt": "2021-02-16T11:04:36.722Z",
      "bumpedAt": "2021-02-16T14:58:53.481Z",
      "solvedPostId": null,
      "likeCount": 1,
      "views": 1600
    },
    {
      "id": 15309,
      "title": "Add ability to expand item view drawer to occupy the entire board view space",
      "slug": "add-ability-to-expand-item-view-drawer-to-occupy-the-entire-board-view-space",
      "excerpt": "Hey, \nThere are many use cases where item views added by apps would have a much better and more feature rich UX if they can occupy more screen space than the current right sided drawer, which is very limited in size. \nMy&hellip;",
      "postsCount": 3,
      "lastPostedAt": "2021-02-15T18:39:53.372Z",
      "createdAt": "2021-01-22T07:48:51.427Z",
      "bumpedAt": "2021-02-15T18:39:53.372Z",
      "solvedPostId": null,
      "likeCount": 1,
      "views": 1452
    },
    {
      "id": 16055,
      "title": "Cross board interaction between two items",
      "slug": "cross-board-interaction-between-two-items",
      "excerpt": "Hi, \nI am trying to build a custom integration recipe where if I update a column’s value in a board where I am going to apply an integration can also change the value in other board I want to(provided in recipe sentence)&hellip;",
      "postsCount": 5,
      "lastPostedAt": "2021-02-15T05:50:44.895Z",
      "createdAt": "2021-02-09T08:04:30.386Z",
      "bumpedAt": "2021-02-15T05:50:44.895Z",
      "solvedPostId": null,
      "likeCount": 0,
      "views": 1114
    },
    {
      "id": 16158,
      "title": "Custom integration fails when I add ssl to network",
      "slug": "custom-integration-fails-when-i-add-ssl-to-network",
      "excerpt": "I have a custom integration which was developed and tested using port 8080. \nAll working well and I have setup on a vm with node server. \nAttempting to implement ssl to secure the traffic and all updates are then failing&hellip;",
      "postsCount": 9,
      "lastPostedAt": "2021-02-12T20:27:35.199Z",
      "createdAt": "2021-02-11T06:50:10.440Z",
      "bumpedAt": "2021-02-12T20:27:35.199Z",
      "solvedPostId": null,
      "likeCount": 0,
      "views": 2299
    },
    {
      "id": 15137,
      "title": "Recipe with Custom Triger, Action and mapping",
      "slug": "recipe-with-custom-triger-action-and-mapping",
      "excerpt": "Trying to create integration with third-party api and update several columns on monday.com side \nI create \n\ncustom type with all required fields\ncustom triger with sunscribe/unsubscribe\ncustom action\n\nand receipt not wor&hellip;",
      "postsCount": 34,
      "lastPostedAt": "2021-02-12T13:56:44.750Z",
      "createdAt": "2021-01-18T14:25:14.566Z",
      "bumpedAt": "2021-02-12T13:56:37.848Z",
      "solvedPostId": null,
      "likeCount": 2,
      "views": 7101
    },
    {
      "id": 10216,
      "title": "API Playground multiple operations error",
      "slug": "api-playground-multiple-operations-error",
      "excerpt": "When using the API Playground GraphiQL interface, it seems like it supports the ability (like the default GraphiQL from Apollo) to have multiple queries in the editor, then choose which one to run. It doesn’t work though&hellip;",
      "postsCount": 6,
      "lastPostedAt": "2021-02-12T03:21:47.477Z",
      "createdAt": "2020-08-18T13:01:41.275Z",
      "bumpedAt": "2021-02-12T03:21:47.477Z",
      "solvedPostId": null,
      "likeCount": 2,
      "views": 3566
    }
  ],
  "total": 3350,
  "offset": 2700,
  "limit": 50
}