{
  "id": 101236,
  "title": "Hide Sum Bar",
  "slug": "hide-sum-bar",
  "categoryId": 6,
  "tagIds": [
    17
  ],
  "createdAt": "2024-10-22T21:05:52.457Z",
  "lastPostedAt": "2024-10-27T22:52:07.751Z",
  "postsCount": 3,
  "excerpt": "Can we hide the sum bar? It doesn’t make sense on my board.",
  "solvedPostId": null,
  "likeCount": 1,
  "views": 40,
  "posts": [
    {
      "id": 206808,
      "postNumber": 1,
      "createdAt": "2024-10-22T21:05:52.526Z",
      "author": "matty.tilbrook (Matty Tilbrook)",
      "cookedHtml": "<p>Can we hide the sum bar? It doesn’t make sense on my board.</p>\n<p></p><div class=\"lightbox-wrapper\"><a class=\"lightbox\" href=\"https://global.discourse-cdn.com/monday/original/3X/9/0/9059a3f3909c9d01001364cf21c4d70fd3a50247.png\" title=\"Capture (1)\" rel=\"noopener nofollow ugc\"><img src=\"https://global.discourse-cdn.com/monday/optimized/3X/9/0/9059a3f3909c9d01001364cf21c4d70fd3a50247_2_690x145.png\" alt=\"Capture (1)\" width=\"690\" height=\"145\" /><div class=\"meta\"><span class=\"filename\">Capture (1)</span><span class=\"informations\">1570×331 48 KB</span></div></a></div><p></p>"
    },
    {
      "id": 206873,
      "postNumber": 2,
      "createdAt": "2024-10-23T07:00:35.848Z",
      "author": "basdebruin (Bas de Bruin)",
      "cookedHtml": "<p>That is a option per column<br />\n</p><div class=\"lightbox-wrapper\"><a class=\"lightbox\" href=\"https://global.discourse-cdn.com/monday/original/3X/c/8/c81420b0e2730de39495ddab29578c51ba19d413.png\" title=\"image\"><img src=\"https://global.discourse-cdn.com/monday/optimized/3X/c/8/c81420b0e2730de39495ddab29578c51ba19d413_2_501x500.png\" alt=\"image\" width=\"501\" height=\"500\" /><div class=\"meta\"><span class=\"filename\">image</span><span class=\"informations\">521×519 30.3 KB</span></div></a></div><p></p>"
    },
    {
      "id": 207437,
      "postNumber": 3,
      "createdAt": "2024-10-27T22:52:07.751Z",
      "author": "matty.tilbrook (Matty Tilbrook)",
      "cookedHtml": "<p>Thank you so much! <img src=\"https://emoji.discourse-cdn.com/apple/grin.png?v=12\" title=\":grin:\" class=\"emoji\" alt=\":grin:\" width=\"20\" height=\"20\" /></p>"
    }
  ]
}