{
  "id": 113523,
  "title": "Access monday's native UI components via SDK",
  "slug": "access-mondays-native-ui-components-via-sdk",
  "categoryId": 8,
  "tagIds": [
    208,
    297,
    351,
    436
  ],
  "createdAt": "2025-04-23T06:24:13.797Z",
  "lastPostedAt": "2025-04-23T06:24:13.878Z",
  "postsCount": 1,
  "excerpt": "I’m new to monday.com app development and I have a question: is it possible to access monday’s native UI components via the SDK or another supported mechanism? \nFor example, I want to create a helper board item menu app &hellip;",
  "solvedPostId": null,
  "likeCount": 0,
  "views": 9,
  "posts": [
    {
      "id": 227610,
      "postNumber": 1,
      "createdAt": "2025-04-23T06:24:13.878Z",
      "author": "edicezar.nanni (Edi Nanni)",
      "cookedHtml": "<p>I’m new to <a href=\"http://monday.com\" rel=\"noopener nofollow ugc\">monday.com</a> app development and I have a question: is it possible to access monday’s native UI components via the SDK or another supported mechanism?</p>\n<p>For example, I want to create a helper <strong>board item menu app</strong> that retrieves information from the item on a board, opens the item card, and inserts this information (as a pre-formatted text) into the text field of a new Update. So far, I’ve been able to retrieve the information via the API and open the item card in the Update tab. Now I need to be able to insert the text in the new update text box.</p>"
    }
  ]
}