{
  "id": 123528,
  "title": "\"Manage Duplicate\" Issue",
  "slug": "manage-duplicate-issue",
  "categoryId": 6,
  "tagIds": [
    22,
    107,
    120
  ],
  "createdAt": "2026-02-06T12:44:09.229Z",
  "lastPostedAt": "2026-02-06T20:05:57.975Z",
  "postsCount": 4,
  "excerpt": "The Manage Duplicates function recently had an issue with displaying the duplicates.  Monday.com fixed this issue but now when I manage duplicates is only allows me to merge 1 set of duplicate items even when it’s displa&hellip;",
  "solvedPostId": null,
  "likeCount": 1,
  "views": 21,
  "posts": [
    {
      "id": 245472,
      "postNumber": 1,
      "createdAt": "2026-02-06T12:44:09.311Z",
      "author": "aclarkO3 (Aaron)",
      "cookedHtml": "<p>The Manage Duplicates function recently had an issue with displaying the duplicates.  <a href=\"http://Monday.com\" rel=\"noopener nofollow ugc\">Monday.com</a> fixed this issue but now when I manage duplicates is only allows me to merge 1 set of duplicate items even when it’s displaying multiple.  Hoping the technical team will see this and make the fix.</p>"
    },
    {
      "id": 245473,
      "postNumber": 2,
      "createdAt": "2026-02-06T12:46:19.469Z",
      "author": "mia-cxmonday (Mia Leath)",
      "cookedHtml": "<p>Hey Aaron,</p>\n<p>Mia here from <a href=\"http://monday.com\">monday.com</a> <img src=\"https://emoji.discourse-cdn.com/apple/smiling_face.png?v=15\" title=\":smiling_face:\" class=\"emoji\" alt=\":smiling_face:\" width=\"20\" height=\"20\" /> I hope you’re doing well!</p>\n<p>Would you be able to DM me your monday account name so we can open up a ticket for you? That’ll allow me to take a closer look and raise this to our Technical Support team if needed. Thank you!</p>"
    },
    {
      "id": 245480,
      "postNumber": 3,
      "createdAt": "2026-02-06T15:21:38.167Z",
      "author": "Clover_Gal (Desiree McCarthy | monday.com Ambassador)",
      "cookedHtml": "<p>I actually just submitted the same issue to support yesterday. They said it was a known issue and that they’d add my account to the list.</p>\n<p>Thanks</p>"
    },
    {
      "id": 245503,
      "postNumber": 4,
      "createdAt": "2026-02-06T20:05:57.975Z",
      "author": "aclarkO3 (Aaron)",
      "cookedHtml": "<p>If I respond here does this DM you or the forum?</p>"
    }
  ]
}