{
  "id": 13271,
  "title": "How to connect my app to the Monday.com workflow/structure",
  "slug": "how-to-connect-my-app-to-the-monday-com-workflow-structure",
  "categoryId": 8,
  "tagIds": [
    208,
    351
  ],
  "createdAt": "2020-11-15T19:38:18.984Z",
  "lastPostedAt": "2020-11-18T19:53:07.318Z",
  "postsCount": 5,
  "excerpt": "I am trying to build on top of Monday for the hackaton. I would like to work with the CRM. But how do I connect to a sales rep list? Do I make a default sales rep list to start from? I am unsure of the workflow here. I h&hellip;",
  "solvedPostId": null,
  "likeCount": 0,
  "views": 1133,
  "posts": [
    {
      "id": 33757,
      "postNumber": 1,
      "createdAt": "2020-11-15T19:38:19.065Z",
      "author": "Harry_X (Harald Carlsten)",
      "cookedHtml": "<p>I am trying to build on top of Monday for the hackaton. I would like to work with the CRM. But how do I connect to a sales rep list? Do I make a default sales rep list to start from? I am unsure of the workflow here. I have an idea of a few views and a flow in my app. I don’t really understand how to connect it to the app in general.</p>"
    },
    {
      "id": 33834,
      "postNumber": 2,
      "createdAt": "2020-11-16T20:17:06.624Z",
      "author": "dsilva (Daniel Silva)",
      "cookedHtml": "<p>Hey <a class=\"mention\" href=\"/u/harry_x\">@Harry_X</a> - combining both threads on here.</p>\n<p>Are you looking to plug into our API, or creating a custom application with our SDK?</p>\n<p>-Daniel</p>"
    },
    {
      "id": 33869,
      "postNumber": 3,
      "createdAt": "2020-11-17T03:45:50.828Z",
      "author": "Harry_X (Harald Carlsten)",
      "cookedHtml": "<p>Hi dsilva! I am using the SDK to make a custom application to work in the CRM set up. I just want to know how I hook it up to Monday’s workflow. Thank you for your time!</p>"
    },
    {
      "id": 34026,
      "postNumber": 4,
      "createdAt": "2020-11-18T19:53:07.318Z",
      "author": "dsilva (Daniel Silva)",
      "cookedHtml": "<p>Hey <a class=\"mention\" href=\"/u/harry_x\">@Harry_X</a> - all information regarding our apps and integrations are available through our <a href=\"https://developers.monday.com/\" rel=\"noopener nofollow ugc\">documentation.</a> I personally recommend starting with the quickstart guides listed there to get an idea of how these apps integrate with monday.</p>\n<p>-Daniel</p>"
    },
    {
      "id": 44587,
      "postNumber": 5,
      "createdAt": "2021-03-12T13:20:32.481Z",
      "author": "system (system)",
      "cookedHtml": "<p>This topic was automatically closed 7 days after the last reply. New replies are no longer allowed.</p>"
    }
  ]
}