{
  "id": 37880,
  "title": "Manually arrange list of options in \"multi-select question\"",
  "slug": "manually-arrange-list-of-options-in-multi-select-question",
  "categoryId": 7,
  "tagIds": [
    462
  ],
  "createdAt": "2022-06-16T13:43:53.344Z",
  "lastPostedAt": "2023-10-12T20:20:24.862Z",
  "postsCount": 5,
  "excerpt": "I’m making a volunteer availability questionnaire and I’d really like to have the options listed as Sunday through Saturday, rather than alphanumerically as seen in the image here.",
  "solvedPostId": null,
  "likeCount": 1,
  "views": 1781,
  "posts": [
    {
      "id": 88838,
      "postNumber": 1,
      "createdAt": "2022-06-16T13:43:53.414Z",
      "author": "eperkinscrcc (E. Perkins)",
      "cookedHtml": "<p></p><div class=\"lightbox-wrapper\"><a class=\"lightbox\" href=\"https://global.discourse-cdn.com/monday/original/2X/a/acb8a17c6d8a54182deed45ae36ecd2df3577b84.png\" title=\"Monday forms - alpha list\" rel=\"noopener nofollow ugc\"><img src=\"https://global.discourse-cdn.com/monday/optimized/2X/a/acb8a17c6d8a54182deed45ae36ecd2df3577b84_2_690x424.png\" alt=\"Monday forms - alpha list\" width=\"690\" height=\"424\" /><div class=\"meta\">\n<span class=\"filename\">Monday forms - alpha list</span><span class=\"informations\">2850×1752 162 KB</span>\n</div></a></div><p></p>\n<p>I’m making a volunteer availability questionnaire and I’d really like to have the options listed as Sunday through Saturday, rather than alphanumerically as seen in the image here.</p>"
    },
    {
      "id": 130683,
      "postNumber": 2,
      "createdAt": "2023-06-07T12:59:25.991Z",
      "author": "samspacher (Shannon)",
      "cookedHtml": "<p>Came here to submit a feature request for this exact issue. Sometimes it’s helpful to have them alphabetized, but it doesn’t always make sense - like with days of the week or listing time slots in chronological order. Please, please, please make this functionality available Monday!!</p>"
    },
    {
      "id": 144619,
      "postNumber": 3,
      "createdAt": "2023-09-20T15:30:42.635Z",
      "author": "christinakelley (Christina Kelley)",
      "cookedHtml": "<p>Was there ever a response from Monday on this?  Because this would be really helpful to be able to arrange items manually.</p>"
    },
    {
      "id": 148094,
      "postNumber": 4,
      "createdAt": "2023-10-12T19:08:39.598Z",
      "author": "jessica1234 (Jessica)",
      "cookedHtml": "<p>I’m working on a form now and I really was hoping there was an option to turn off the alphabetic order of these options.</p>\n<p>For example, I’ve added a “none of the above” option, but it does not look right because this phrase starts with the letter “N” and due to the auto-ordering of the options, it will not be the last option.</p>"
    },
    {
      "id": 148115,
      "postNumber": 5,
      "createdAt": "2023-10-12T20:20:24.862Z",
      "author": "MikeB_Axanexa (Mike Buckiewicz)",
      "cookedHtml": "<p>Hi All!</p>\n<p>I have used numbers before to keep the order I want in front of the selections. Not ideal but then you can dictate the order with numerical value. Like seen here:</p>\n<p></p><div class=\"lightbox-wrapper\"><a class=\"lightbox\" href=\"https://global.discourse-cdn.com/monday/original/3X/0/e/0e926a1ec1c09d081950062dbda36e34ae8bff78.png\" title=\"image\" rel=\"noopener nofollow ugc\"><img src=\"https://global.discourse-cdn.com/monday/optimized/3X/0/e/0e926a1ec1c09d081950062dbda36e34ae8bff78_2_579x499.png\" alt=\"image\" width=\"579\" height=\"499\" /><div class=\"meta\"><span class=\"filename\">image</span><span class=\"informations\">1230×1062 25 KB</span></div></a></div><p></p>\n<p>Hope this helps!</p>\n<p>Mike B<br />\nAutomation Architect</p>"
    }
  ]
}