{
  "id": 58937,
  "title": "Live Sync Google Sheet to Monday Board",
  "slug": "live-sync-google-sheet-to-monday-board",
  "categoryId": 8,
  "tagIds": [
    22,
    209,
    351,
    355
  ],
  "createdAt": "2023-05-24T11:11:11.665Z",
  "lastPostedAt": "2024-12-19T07:59:18.735Z",
  "postsCount": 17,
  "excerpt": "Hello, \nI’m looking for some advice on whether it’s possible to connect a google sheet (that gets updated every hour) to a monday board. \nMy google sheet has columns that update every hour but the first column that conta&hellip;",
  "solvedPostId": null,
  "likeCount": 8,
  "views": 5196,
  "posts": [
    {
      "id": 129283,
      "postNumber": 1,
      "createdAt": "2023-05-24T11:11:11.784Z",
      "author": "WTagreen (Alex Green)",
      "cookedHtml": "<p>Hello,</p>\n<p>I’m looking for some advice on whether it’s possible to connect a google sheet (that gets updated every hour) to a monday board.</p>\n<p>My google sheet has columns that update every hour but the first column that contain the name of an item always remains the same.</p>\n<p>Essentially what I’m looking to do is have some Monday columns also update either hourly or once a day for the relevant item which will match the item name in google sheets.</p>\n<p>When a new line is created in the google sheet then that would also be created into my Monday board and then the update would kick in.</p>\n<p>TIA<br />\nAlex</p>"
    },
    {
      "id": 129294,
      "postNumber": 2,
      "createdAt": "2023-05-24T11:48:33.802Z",
      "author": "Juandres (Juan)",
      "cookedHtml": "<p>It’s possible with Make, but there are small costs involved.</p>\n<p></p><div class=\"lightbox-wrapper\"><a class=\"lightbox\" href=\"https://global.discourse-cdn.com/monday/original/3X/c/d/cd13e969ec241197757bacff64613fa55436961d.png\" title=\"Screenshot 2023-05-24 104557\" rel=\"noopener nofollow ugc\"><img src=\"https://global.discourse-cdn.com/monday/optimized/3X/c/d/cd13e969ec241197757bacff64613fa55436961d_2_690x175.png\" alt=\"Screenshot 2023-05-24 104557\" width=\"690\" height=\"175\" /><div class=\"meta\">\n<span class=\"filename\">Screenshot 2023-05-24 104557</span><span class=\"informations\">1443×367 31.5 KB</span>\n</div></a></div><p></p>"
    },
    {
      "id": 129716,
      "postNumber": 3,
      "createdAt": "2023-05-29T10:13:12.845Z",
      "author": "Matias.Monday (Matias)",
      "cookedHtml": "<p>exclude_reply_from_sla</p>"
    },
    {
      "id": 130456,
      "postNumber": 4,
      "createdAt": "2023-06-06T08:10:39.379Z",
      "author": "Mannetjie (Klaas J Van Rooyen)",
      "cookedHtml": "<p>This is very possible using AppScript in Google Sheets and using triggers. Hit me up if you need help</p>"
    },
    {
      "id": 130479,
      "postNumber": 5,
      "createdAt": "2023-06-06T10:44:12.822Z",
      "author": "Matias.Monday (Matias)",
      "cookedHtml": "<p>exclude_reply_from_sla</p>"
    },
    {
      "id": 158434,
      "postNumber": 6,
      "createdAt": "2023-12-18T12:58:32.207Z",
      "author": "resynced.io (Andriy Obrizan)",
      "cookedHtml": "<p>We’re working on <a href=\"https://resynced.io/\" rel=\"noopener nofollow ugc\">resynced.io</a>, an app for live two-way data synchronization between multiple apps that would be able to do that:</p>\n<ul>\n<li>Connect your Google sheet and the <a href=\"http://monday.com\" rel=\"noopener nofollow ugc\">monday.com</a> board</li>\n<li>Select columns to match items and rows</li>\n<li>Map a column in Sheets to a column on the board, and check that it should only be updated in one direction</li>\n<li>Enable adding new <a href=\"http://monday.com\" rel=\"noopener nofollow ugc\">monday.com</a> items from the sheet’s rows</li>\n</ul>"
    },
    {
      "id": 158577,
      "postNumber": 7,
      "createdAt": "2023-12-19T09:52:29.624Z",
      "author": "TomFri (Tom Fridman)",
      "cookedHtml": "<p>Hi <a class=\"mention\" href=\"/u/resynced.io\">@resynced.io</a></p>\n<p>Welcome to the community and thank you for sharing with us.</p>\n<p>What stage is your app at? Is it on review yet?</p>"
    },
    {
      "id": 158603,
      "postNumber": 8,
      "createdAt": "2023-12-19T13:22:29.103Z",
      "author": "resynced.io (Andriy Obrizan)",
      "cookedHtml": "<p>The app is still being developed.</p>\n<p>We started with Google Sheets to <a href=\"http://monday.com\" rel=\"noopener nofollow ugc\">monday.com</a> synchronization app with limited functionality and then decided to expand the idea. Unfortunately, it will take some time.</p>"
    },
    {
      "id": 158608,
      "postNumber": 9,
      "createdAt": "2023-12-19T13:51:36.573Z",
      "author": "TomFri (Tom Fridman)",
      "cookedHtml": "<p>Love that!<br />\nIf you would like to here feedback from the marketplace team you are always welcome to register to a pitch your app session. <a href=\"https://wkf.ms/4781UVr\" class=\"inline-onebox\">Pitch your App registration</a></p>"
    },
    {
      "id": 159307,
      "postNumber": 10,
      "createdAt": "2023-12-27T10:54:26.725Z",
      "author": "rodneyz (Rodney)",
      "cookedHtml": "<p>Hi <a class=\"mention\" href=\"/u/wtagreen\">@WTagreen</a> , have you tried <strong>Google Sheets Automations by Formula Lookout</strong>? This app have everything you need for syncing your Google Sheet.</p>"
    },
    {
      "id": 159318,
      "postNumber": 11,
      "createdAt": "2023-12-27T11:14:00.005Z",
      "author": "Matias.Monday (Matias)",
      "cookedHtml": "<p>exclude_reply_from_sla</p>"
    },
    {
      "id": 159840,
      "postNumber": 12,
      "createdAt": "2024-01-02T13:25:24.819Z",
      "author": "WTagreen (Alex Green)",
      "cookedHtml": "<p>Looks like that will just sync monday items over to Google Sheets. I need to sync a google sheet document into Monday items</p>"
    },
    {
      "id": 159975,
      "postNumber": 13,
      "createdAt": "2024-01-03T11:11:06.622Z",
      "author": "Matias.Monday (Matias)",
      "cookedHtml": "<p>exclude_reply_from_sla</p>"
    },
    {
      "id": 166768,
      "postNumber": 14,
      "createdAt": "2024-02-08T15:40:19.781Z",
      "author": "ericmdrnrv (Eric)",
      "cookedHtml": "<p>Any update on when it will be ready or testers will be allowed access?</p>"
    },
    {
      "id": 167412,
      "postNumber": 15,
      "createdAt": "2024-02-12T19:48:50.708Z",
      "author": "Mykola (Mykola Pustovoychenko)",
      "cookedHtml": "<p>Hi Eric,</p>\n<p>We already have working sync core. At the moment, we’re focused on UI/UX of synchronization setup and other essential pieces of functionality like dashboard, statuses of running integrations, etc.</p>\n<p>As soon as <a href=\"http://resynced.io\" rel=\"noopener nofollow ugc\">resynced.io</a> is ready for closed testing I’ll reach out to you</p>"
    },
    {
      "id": 167625,
      "postNumber": 16,
      "createdAt": "2024-02-13T17:39:41.175Z",
      "author": "WZ_Cisco (WZ)",
      "cookedHtml": "<p>+1 <a class=\"mention\" href=\"/u/mykola\">@Mykola</a>. Also interested in alpha/beta testing the tool.</p>"
    },
    {
      "id": 167813,
      "postNumber": 17,
      "createdAt": "2024-02-14T12:58:40.179Z",
      "author": "WZ_Cisco (WZ)",
      "cookedHtml": "<p>Hi Klaas, would you mind sharing your code with me?</p>"
    },
    {
      "id": 167882,
      "postNumber": 18,
      "createdAt": "2024-02-14T14:26:14.918Z",
      "author": "Matias.Monday (Matias)",
      "cookedHtml": "<p>exclude_reply_from_sla</p>"
    },
    {
      "id": 179803,
      "postNumber": 19,
      "createdAt": "2024-04-19T13:49:56.982Z",
      "author": "JoshFromUnito (Hugh Neato)",
      "cookedHtml": "<p>Hi Alex,</p>\n<p>It’s possible <em>and</em> there are options out there to connect your apps without having to write script of any kind to get regular updates in both <a href=\"http://monday.com\" rel=\"noopener nofollow ugc\">monday.com</a> and Google Sheets.</p>\n<p>You can try out the <a href=\"https://monday.com/marketplace/11\" rel=\"noopener nofollow ugc\">Unito app from the monday.com marketplace</a>.</p>\n<p>Here’s how it works:</p>\n<ol>\n<li>Get the app from the monday marketplace</li>\n<li>Connect monday and Google Sheets to Unito</li>\n<li>Pick a flow direction: this tells the integration to either create new tasks when you create spreadsheet rows, vice versa, or both.</li>\n<li>Add rules to filter out unrelated tasks or rows.</li>\n<li>Link fields between each tool so Unito knows where to put your monday fields (title, description, etc.) in the connected spreadsheet.</li>\n</ol>\n<p>Here’s a <a href=\"https://bit.ly/mondaysheets\" rel=\"noopener nofollow ugc\">tutorial</a> explaining how it works with more detail. Hope it helps.</p>\n<p>Hope it helps.</p>"
    },
    {
      "id": 180172,
      "postNumber": 20,
      "createdAt": "2024-04-22T11:36:35.323Z",
      "author": "AleksOrbital (Aleks Zheleznov)",
      "cookedHtml": "<p>Hello, do you still have the code for this?</p>"
    },
    {
      "id": 180643,
      "postNumber": 21,
      "createdAt": "2024-04-24T10:01:20.335Z",
      "author": "Matias.Monday (Matias)",
      "cookedHtml": "<p>exclude_reply_from_sla</p>"
    },
    {
      "id": 201902,
      "postNumber": 22,
      "createdAt": "2024-09-20T14:01:09.824Z",
      "author": "jamespatten (James Patten)",
      "cookedHtml": "<p>If you’re looking for a solution that doesn’t require scripts or building workflows, then check out the <a href=\"https://monday.com/marketplace/listing/10000557/data-importer\" rel=\"noopener nofollow ugc\">Data Importer monday app.</a></p>\n<p>You can import from a Google Sheet into a new or existing monday board, and set-up a schedule such that it syncs your data every hour.</p>\n<p>I’ve created <a href=\"https://dataimporter.co/blog/integrate-google-sheets-monday\" rel=\"noopener nofollow ugc\">a tutorial</a> on specifically how to do this.</p>\n<p></p><div class=\"lightbox-wrapper\"><a class=\"lightbox\" href=\"https://global.discourse-cdn.com/monday/original/3X/2/a/2a0a0a2b5e393cb0598860f97f35aa4a738550bd.png\" title=\"image\" rel=\"noopener nofollow ugc\"><img src=\"https://global.discourse-cdn.com/monday/optimized/3X/2/a/2a0a0a2b5e393cb0598860f97f35aa4a738550bd_2_690x431.png\" alt=\"image\" width=\"690\" height=\"431\" /><div class=\"meta\"><span class=\"filename\">image</span><span class=\"informations\">2084×1302 173 KB</span></div></a></div><p></p>"
    },
    {
      "id": 202005,
      "postNumber": 23,
      "createdAt": "2024-09-22T12:06:22.150Z",
      "author": "Matias.Monday (Matias)",
      "cookedHtml": "<p>exclude_reply_from_sla</p>"
    },
    {
      "id": 214692,
      "postNumber": 24,
      "createdAt": "2024-12-19T07:59:18.735Z",
      "author": "Mykola (Mykola Pustovoychenko)",
      "cookedHtml": "<p>Hi Alex,</p>\n<p>Finally, we’re in open beta. Feel free to try the app here: <a href=\"https://app.resynced.io/\" rel=\"noopener nofollow ugc\">https://app.resynced.io/</a><br />\nQuick Start Guide: <a href=\"https://resynced.io/quickstart\" class=\"inline-onebox\" rel=\"noopener nofollow ugc\">resynced.io - Quickstart Page</a></p>\n<p>The app is already approved and published in <a href=\"http://monday.com\" rel=\"noopener nofollow ugc\">monday.com</a> marketplace.</p>\n<p>Should you have any questions feel free to reach out. We’re happy to help.</p>\n<p><a class=\"mention\" href=\"/u/wz_cisco\">@WZ_Cisco</a> <a class=\"mention\" href=\"/u/ericmdrnrv\">@ericmdrnrv</a> tagging you, since you were interested.</p>"
    },
    {
      "id": 214987,
      "postNumber": 25,
      "createdAt": "2024-12-22T09:02:24.368Z",
      "author": "Matias.Monday (Matias)",
      "cookedHtml": "<p>exclude_reply_from_sla</p>"
    }
  ]
}