{
  "id": 59206,
  "title": "A glimpse of the new monday.com data infrastructure",
  "slug": "a-glimpse-of-the-new-monday-com-data-infrastructure",
  "categoryId": 68,
  "tagIds": [
    245,
    246
  ],
  "createdAt": "2023-05-30T12:38:34.367Z",
  "lastPostedAt": "2023-07-06T16:15:21.212Z",
  "postsCount": 7,
  "excerpt": "In am excited to share with you one of the most exciting updates to our platform! Our team has been hard at work building mondayDB, a new data infrastructure, designed to drive your best work by: \n\nSupporting a larger sc&hellip;",
  "solvedPostId": null,
  "likeCount": 6,
  "views": 1708,
  "posts": [
    {
      "id": 129830,
      "postNumber": 1,
      "createdAt": "2023-05-30T12:38:34.456Z",
      "author": "Julietteb (Juliette )",
      "cookedHtml": "<p>In am excited to share with you one of the most exciting updates to our platform! Our team has been hard at work building mondayDB, a new data infrastructure, designed to drive your best work by:</p>\n<ul>\n<li>Supporting a larger scale of boards and dashboards at speed</li>\n<li>Extending our public API and data manipulation capabilities,</li>\n<li>supporting countless new use cases and custom workflows</li>\n</ul>\n<p>While you won’t be able to see mondayDB, you will be able to feel it and will get a notification when it is added. Check it out!</p>\n<div class=\"youtube-onebox lazy-video-container\">\n  <a href=\"https://www.youtube.com/watch?v=O2ZM057S8lA\" target=\"_blank\" rel=\"noopener\">\n    <img class=\"youtube-thumbnail\" src=\"https://global.discourse-cdn.com/monday/original/3X/c/b/cb0575c772112275c7a069c9e0e99aa9e20e9c3e.jpeg\" title=\"Introducing mondayDB 1.0 | monday.com\" width=\"690\" height=\"388\" />\n  </a>\n</div>\n\n<p>More info about mondayDB <a href=\"https://monday.com/ap/mondaydb?_ga=2.246755588.1478127948.1685359691-1153131673.1655720675&amp;_gac=1.13766341.1682342687.CjwKCAjw0ZiiBhBKEiwA4PT9z7m9KUNo2JtRIg4eEti4HJJ0s0y909x9sc9nOVxbcs7Q-0Zm4j6QQxoCRo8QAvD_BwE\">here.</a></p>"
    },
    {
      "id": 130170,
      "postNumber": 3,
      "createdAt": "2023-06-02T02:26:07.311Z",
      "author": "Terry.Heard (Terry Heard)",
      "cookedHtml": "<p>Hi Juliette. I see that the release date for DB1.0 is this month. Is that on schedule to happen?</p>"
    },
    {
      "id": 130708,
      "postNumber": 4,
      "createdAt": "2023-06-07T18:11:05.968Z",
      "author": "Cyrille (L)",
      "cookedHtml": "<p>Hello Juliette. What are Aggretations that are scheduled in version 1.2? Thanks!</p>"
    },
    {
      "id": 130715,
      "postNumber": 5,
      "createdAt": "2023-06-07T21:18:29.958Z",
      "author": "BiancaT (Bianca Taylor)",
      "cookedHtml": "<p>Hey Terry - yes it sure, this first version is already being rolled out! You should start to recognise its impact when loading larger boards and you’ll receive a notification when it’s rolled out to your account <img src=\"https://emoji.discourse-cdn.com/apple/raised_hands.png?v=12\" title=\":raised_hands:\" class=\"emoji\" alt=\":raised_hands:\" width=\"20\" height=\"20\" /></p>"
    },
    {
      "id": 130800,
      "postNumber": 6,
      "createdAt": "2023-06-08T15:03:00.384Z",
      "author": "RaymondChin (Raymond Chin)",
      "cookedHtml": "<p>What about item cards?<br />\nI have a board of 6-7k contacts that loads relatively quickly, but when I try opening the overview, it takes a good 25+ seconds to load, for at least the first time.</p>\n<p>When I share a link to an item card, the loading latency gives the visitor just enough time to click <em>out</em> of the item page view and cause the item page to never show up.</p>"
    },
    {
      "id": 131138,
      "postNumber": 7,
      "createdAt": "2023-06-12T23:12:54.709Z",
      "author": "BiancaT (Bianca Taylor)",
      "cookedHtml": "<p><a class=\"mention\" href=\"/u/raymondchin\">@RaymondChin</a> Hey! Hm, 25 seconds is a fairly decent loading time…which means this might need our support teams attention. Would you be happy to send us a private message with a few more details about this behaviour (i.e. does this only occur on this board? Does the same behaviour occur in an incognito window)? <img src=\"https://emoji.discourse-cdn.com/apple/pray.png?v=12\" title=\":pray:\" class=\"emoji\" alt=\":pray:\" width=\"20\" height=\"20\" /></p>"
    },
    {
      "id": 134087,
      "postNumber": 8,
      "createdAt": "2023-07-06T16:15:21.212Z",
      "author": "theshiftybadger (Chase Baker)",
      "cookedHtml": "<p>hey there!  is there a way tenant admins can validate if MondayDB has been enabled for their account?  wouldn’t be surprised if some of us may miss the initial notification <img src=\"https://emoji.discourse-cdn.com/apple/joy.png?v=12\" title=\":joy:\" class=\"emoji\" alt=\":joy:\" width=\"20\" height=\"20\" /></p>"
    }
  ]
}