{
  "id": 59527,
  "title": "I want to add a small description of updates inside updates section",
  "slug": "i-want-to-add-a-small-description-of-updates-inside-updates-section",
  "categoryId": 8,
  "tagIds": [
    94,
    351
  ],
  "createdAt": "2023-06-06T07:11:29.822Z",
  "lastPostedAt": "2023-06-25T10:41:53.122Z",
  "postsCount": 20,
  "excerpt": "I have created the app using reactJS that works with monday. But I can not find that app anywhere and also if i did find the app, I do not want a separate view for my app. \nI want to update the view of updates. How can I&hellip;",
  "solvedPostId": null,
  "likeCount": 0,
  "views": 430,
  "posts": [
    {
      "id": 130447,
      "postNumber": 1,
      "createdAt": "2023-06-06T07:11:29.908Z",
      "author": "70shakeel (Muhammad Shakeel ur Rehman Tariq)",
      "cookedHtml": "<p>I have created the app using reactJS that works with monday. But I can not find that app anywhere and also if i did find the app, I do not want a separate view for my app.<br />\nI want to update the view of updates. How can I achieve that?<br />\nFor now I have created an app and built a Board view feature and then in ReactJS quickstart I have made some changes and then published the app, but I can not find the app when I try to add it. Also, I am thinking even if I find the app, I won’t be able to see that inside the updates section.<br />\nI want to be able to edit the updates section. How can I achieve that?<br />\nThanks.</p>"
    },
    {
      "id": 130491,
      "postNumber": 2,
      "createdAt": "2023-06-06T11:47:50.726Z",
      "author": "Matias.Monday (Matias)",
      "cookedHtml": "<p>Hello there <a class=\"mention\" href=\"/u/70shakeel\">@70shakeel</a> and welcome to the community!</p>\n<p>I hope you like it here <img src=\"https://emoji.discourse-cdn.com/apple/muscle.png?v=12\" title=\":muscle:\" class=\"emoji\" alt=\":muscle:\" width=\"20\" height=\"20\" /></p>\n<p>There is no way of adding a view in the updates section. The only way to use the updates section is using the UI in a regular way.</p>\n<p>Regarding your board view not appearing, are you searching for the name of the app when you try to add a board view to your board? Or are you searching for the name of the board view feature? You need to search for the name of the board view feature.</p>\n<p>Looking forward to hearing from you <img src=\"https://emoji.discourse-cdn.com/apple/slightly_smiling_face.png?v=12\" title=\":slightly_smiling_face:\" class=\"emoji\" alt=\":slightly_smiling_face:\" width=\"20\" height=\"20\" /></p>\n<p>Cheers,<br />\nMatias</p>"
    },
    {
      "id": 130500,
      "postNumber": 3,
      "createdAt": "2023-06-06T12:20:23.972Z",
      "author": "70shakeel (Muhammad Shakeel ur Rehman Tariq)",
      "cookedHtml": "<p>So, I can not summarize my updates inside of the updates view?</p>"
    },
    {
      "id": 130511,
      "postNumber": 4,
      "createdAt": "2023-06-06T13:16:58.783Z",
      "author": "Matias.Monday (Matias)",
      "cookedHtml": "<p>Hello again,</p>\n<p>You can create an item view, which would “live” next to the updates, kind of like the item card as explained <a href=\"https://support.monday.com/hc/en-us/articles/360017143959-The-Item-Card-\">here</a>.</p>"
    },
    {
      "id": 130596,
      "postNumber": 5,
      "createdAt": "2023-06-07T02:47:05.997Z",
      "author": "70shakeel (Muhammad Shakeel ur Rehman Tariq)",
      "cookedHtml": "<p>Okay, how can I create an item view?</p>"
    },
    {
      "id": 130605,
      "postNumber": 6,
      "createdAt": "2023-06-07T02:56:07.904Z",
      "author": "70shakeel (Muhammad Shakeel ur Rehman Tariq)",
      "cookedHtml": "<p>I can not find anything related to Item view.</p>"
    },
    {
      "id": 130617,
      "postNumber": 7,
      "createdAt": "2023-06-07T03:52:02.111Z",
      "author": "Matias.Monday (Matias)",
      "cookedHtml": "<p>Hello again,</p>\n<p>You can create an item view by clicking on your avatar or initials at the bottom left of the screen, then on “Developers”, then create an app, and then on the left pane, add a feature. You will see the item view option.</p>\n<p>You can use <a href=\"https://developer.monday.com/apps/docs/quickstart-view\">this quickstart guide</a> as an example.</p>\n<p>Let me know if you have any other questions!</p>\n<p>Cheers,<br />\nMatias</p>"
    },
    {
      "id": 130618,
      "postNumber": 8,
      "createdAt": "2023-06-07T04:04:57.866Z",
      "author": "70shakeel (Muhammad Shakeel ur Rehman Tariq)",
      "cookedHtml": "<p>Thanks, I created an item view and pasted the react code.<br />\nNow I only have one issue.<br />\nHow can I get corresponding update data?<br />\nFor example now it is showing all of the updates.<br />\nI want to be able to show the corresponding updates according to the item.</p>"
    },
    {
      "id": 130724,
      "postNumber": 9,
      "createdAt": "2023-06-08T02:10:47.672Z",
      "author": "70shakeel (Muhammad Shakeel ur Rehman Tariq)",
      "cookedHtml": "<p>How can I select corresponding board in an item view?</p>"
    },
    {
      "id": 130750,
      "postNumber": 10,
      "createdAt": "2023-06-08T07:22:14.491Z",
      "author": "Matias.Monday (Matias)",
      "cookedHtml": "<p>Hello again,</p>\n<p>You can use our SDK to g<a href=\"https://developer.monday.com/apps/docs/mondayget\">et the data of the context</a> where your view is being used and if you need any data from the item itself like the column values in it, you can also use the SDK to <a href=\"https://developer.monday.com/apps/docs/mondayapi\">query for that information</a>.</p>\n<p>Cheers,<br />\nMatias</p>"
    },
    {
      "id": 130884,
      "postNumber": 11,
      "createdAt": "2023-06-09T10:04:48.896Z",
      "author": "70shakeel (Muhammad Shakeel ur Rehman Tariq)",
      "cookedHtml": "<p>I have tried monday.get but it does not seem to work.<br />\nI have used monday.get(“itemIds”).then(res =&gt; console.log(res));<br />\nas mentioned in the docs but still there is no result.<br />\nI have installed npm package as mention in docs<br />\nnpm install monday-sdk-js --save<br />\nimport mondaySdk from “monday-sdk-js”;<br />\nconst monday = mondaySdk();<br />\nStill there is no output.<br />\nI am using it in the app inside item view.</p>"
    },
    {
      "id": 130977,
      "postNumber": 12,
      "createdAt": "2023-06-11T10:16:58.684Z",
      "author": "Matias.Monday (Matias)",
      "cookedHtml": "<p>Hello again,</p>\n<p>Would you be able to please send an email to <a href=\"mailto:appsupport@monday.com\">appsupport@monday.com</a> including a screen recording showing your script, the steps you are taking and the result you see?</p>\n<p>We can take a closer look from there and open a report if needed.</p>\n<p>Looking forward to hearing from you over email!</p>\n<p>Cheers,<br />\nMatias</p>"
    },
    {
      "id": 130986,
      "postNumber": 13,
      "createdAt": "2023-06-11T11:46:34.678Z",
      "author": "70shakeel (Muhammad Shakeel ur Rehman Tariq)",
      "cookedHtml": "<p>Hey, monday.context() worked for me.<br />\nsomehow monday.get() was not working but I achieved the results I needed with monday.context().</p>"
    },
    {
      "id": 131036,
      "postNumber": 14,
      "createdAt": "2023-06-12T05:53:57.801Z",
      "author": "Matias.Monday (Matias)",
      "cookedHtml": "<p>Hello <a class=\"mention\" href=\"/u/70shakeel\">@70shakeel</a>,</p>\n<p>Can you please share the script in which you are using this?</p>"
    },
    {
      "id": 131243,
      "postNumber": 15,
      "createdAt": "2023-06-13T10:17:31.341Z",
      "author": "70shakeel (Muhammad Shakeel ur Rehman Tariq)",
      "cookedHtml": "<p>Sorry, I had a typo in my last reply. I meant to say monday.get(“context”) worked for me.<br />\nP.S. I am unable to use document and window object from my item view app. Why is that and what is the solution to use document.getElementById or any other query selector?<br />\nThanks</p>"
    },
    {
      "id": 131692,
      "postNumber": 16,
      "createdAt": "2023-06-16T05:59:03.200Z",
      "author": "70shakeel (Muhammad Shakeel ur Rehman Tariq)",
      "cookedHtml": "<p>Hey, I am still waiting on your reply on how to use window and document object inside an item view?<br />\nThanks</p>"
    },
    {
      "id": 131832,
      "postNumber": 17,
      "createdAt": "2023-06-18T05:23:22.744Z",
      "author": "Matias.Monday (Matias)",
      "cookedHtml": "<p>Hello again,</p>\n<p>Matias here! Sorry for the late reply.</p>\n<p>Would you be able to send this with the full script you are trying to use to <a href=\"mailto:appsupport@monday.com\">appsupport@monday.com</a> so we can take a closer look into it from there?</p>\n<p>Looking forward to hearing from you via email!</p>\n<p>Cheers,<br />\nMatias</p>"
    },
    {
      "id": 132144,
      "postNumber": 18,
      "createdAt": "2023-06-20T11:14:28.919Z",
      "author": "70shakeel (Muhammad Shakeel ur Rehman Tariq)",
      "cookedHtml": "<p></p><div class=\"lightbox-wrapper\"><a class=\"lightbox\" href=\"https://global.discourse-cdn.com/monday/original/3X/5/8/58f81cf1cf83853c10b87cdc1b493fb5d396b71a.png\" title=\"image\" rel=\"noopener nofollow ugc\"><img src=\"https://global.discourse-cdn.com/monday/optimized/3X/5/8/58f81cf1cf83853c10b87cdc1b493fb5d396b71a_2_690x308.png\" alt=\"image\" width=\"690\" height=\"308\" /><div class=\"meta\">\n<span class=\"filename\">image</span><span class=\"informations\">1009×451 28.4 KB</span>\n</div></a></div><br />\nI have sent the query.<br />\nNow I am facing this issue where my api key is only working on my workspace and not working on any other workspace.<p></p>"
    },
    {
      "id": 132485,
      "postNumber": 19,
      "createdAt": "2023-06-22T05:31:41.772Z",
      "author": "70shakeel (Muhammad Shakeel ur Rehman Tariq)",
      "cookedHtml": "<p>Any news on how my item view app can retrieve item updates respective to the workspace it is installed in?<br />\nAny other way to retrieve updates other than <a href=\"http://monday.com\" rel=\"noopener nofollow ugc\">monday.com</a> api?<br />\nIs there a way to retrieve updates in item view using monday SDK?</p>"
    },
    {
      "id": 132728,
      "postNumber": 20,
      "createdAt": "2023-06-25T10:41:53.122Z",
      "author": "Matias.Monday (Matias)",
      "cookedHtml": "<p>Hello there <a class=\"mention\" href=\"/u/70shakeel\">@70shakeel</a>,</p>\n<p>I see you could resolve the issue with Tyler via email <img src=\"https://emoji.discourse-cdn.com/apple/grin.png?v=12\" title=\":grin:\" class=\"emoji\" alt=\":grin:\" width=\"20\" height=\"20\" /></p>\n<p>Cheers,<br />\nMatias</p>"
    }
  ]
}