{
  "id": 80938,
  "title": "Setting a Column's Visibility from a list of Views",
  "slug": "setting-a-columns-visibility-from-a-list-of-views",
  "categoryId": 7,
  "tagIds": [
    13,
    38
  ],
  "createdAt": "2024-03-13T02:41:43.202Z",
  "lastPostedAt": "2024-03-13T02:41:43.283Z",
  "postsCount": 1,
  "excerpt": "I have a simple Quality of Life request, with regards from showing/hiding columns from views. Currently you can switch to a view, and choose which columns are shown/hidden from that view. I’d like to request the ability &hellip;",
  "solvedPostId": null,
  "likeCount": 0,
  "views": 563,
  "posts": [
    {
      "id": 172953,
      "postNumber": 1,
      "createdAt": "2024-03-13T02:41:43.283Z",
      "author": "EricBarker (Eric Barker)",
      "cookedHtml": "<p>I have a simple Quality of Life request, with regards from showing/hiding columns from views. Currently you can switch to a view, and choose which columns are shown/hidden from that view. I’d like to request the ability to set a single column’s visibility from a list of views. This could be done from a new popup window under the Column &gt; Settings dropdown.</p>\n<p>This would be really helpful on larger boards with multiple users/views. When a new column is created, its creator is currently obligated to cycle through views and toggle the column’s visibility. This breeds hesitation to create new columns in large frameworks. I figure this would be a very useful way of showing/hiding views for a number of different situations.</p>\n<p>For example: I’ve created a new column specifically for a video editor that performs final delivery encoding. I have some basic instructions for this task, but no one else needs to see those. After creating the column, I could go to its settings and can check OFF for all the views, except for her “Encoding view”.</p>\n<p>I’ve created a simple mockup of what this would look like. For simplicity, I’ve only created 3 views, but in reality our company has about a dozen views, and rising, which makes this feature all more helpful:<br />\n</p><div class=\"lightbox-wrapper\"><a class=\"lightbox\" href=\"https://global.discourse-cdn.com/monday/original/3X/1/d/1d9013a97acd5dc295b50dcc404706d75fbd1bda.jpeg\" title=\"ColumnVisibility Screenshot\" rel=\"noopener nofollow ugc\"><img src=\"https://global.discourse-cdn.com/monday/optimized/3X/1/d/1d9013a97acd5dc295b50dcc404706d75fbd1bda_2_690x208.jpeg\" alt=\"ColumnVisibility Screenshot\" width=\"690\" height=\"208\" /><div class=\"meta\"><span class=\"filename\">ColumnVisibility Screenshot</span><span class=\"informations\">1920×581 97.9 KB</span></div></a></div><p></p>"
    }
  ]
}