{
  "id": 98092,
  "title": "Pasting from tables or excel into Monday boards",
  "slug": "pasting-from-tables-or-excel-into-monday-boards",
  "categoryId": 7,
  "tagIds": [
    22
  ],
  "createdAt": "2024-09-20T15:04:23.292Z",
  "lastPostedAt": "2024-09-20T15:04:23.399Z",
  "postsCount": 1,
  "excerpt": "It would be really helpful to be able to cut and paste columns or rows of content into Monday boards.  We often have to consolidate information from various sources and add to a board over time - especially to subitems. &hellip;",
  "solvedPostId": null,
  "likeCount": 0,
  "views": 24,
  "posts": [
    {
      "id": 201916,
      "postNumber": 1,
      "createdAt": "2024-09-20T15:04:23.399Z",
      "author": "Tiff (Tiffany Brunetti Monroe)",
      "cookedHtml": "<p>It would be really helpful to be able to cut and paste columns or rows of content into Monday boards.  We often have to consolidate information from various sources and add to a board over time - especially to subitems.  While you can paste in the first column of subitems, it would be ideal to paste into all columns.</p>"
    }
  ]
}